jaxkan/__init__.py
jaxkan/grids/BaseGrid.py
jaxkan/grids/RBFGrid.py
jaxkan/grids/SplineGrid.py
jaxkan/grids/__init__.py
jaxkan/layers/Chebyshev.py
jaxkan/layers/Dense.py
jaxkan/layers/Fourier.py
jaxkan/layers/Legendre.py
jaxkan/layers/RBF.py
jaxkan/layers/Sine.py
jaxkan/layers/Spline.py
jaxkan/layers/__init__.py
jaxkan/layers/utils.py
jaxkan/models/ActNet.py
jaxkan/models/KAN.py
jaxkan/models/KKAN.py
jaxkan/models/RGAKAN.py
jaxkan/models/__init__.py
jaxkan/models/utils.py
jaxkan/pikan/__init__.py
jaxkan/pikan/adaptive.py
jaxkan/pikan/pde.py
jaxkan/pikan/sampling.py
jaxkan/pikan/utils.py
jaxkan-0.3.5.dist-info/licenses/LICENSE
jaxkan-0.3.5.dist-info/METADATA
jaxkan-0.3.5.dist-info/WHEEL
jaxkan-0.3.5.dist-info/top_level.txt
jaxkan-0.3.5.dist-info/RECORD
