Metadata-Version: 2.4
Name: jaxkan
Version: 0.3.5
Summary: A JAX implementation of Kolmogorov-Arnold Networks
Author-email: Spyros Rigas <rigassp@gmail.com>, Michalis Papachristou <mixpap@phys.uoa.gr>
License: MIT License
Project-URL: Repository, https://github.com/srigas/jaxkan
Project-URL: Issues, https://github.com/srigas/jaxkan/issues
Keywords: JAX,NNX,KANs,Kolmogorov-Arnold,PIKAN
Classifier: Intended Audience :: Science/Research
Classifier: Programming Language :: Python :: 3.11
Classifier: Programming Language :: Python :: 3.12
Classifier: License :: OSI Approved :: MIT License
Requires-Python: <3.13,>=3.11
License-File: LICENSE
Requires-Dist: numpy>=2.3.5
Requires-Dist: scipy>=1.16.3
Requires-Dist: jax[cpu]>=0.8.1
Requires-Dist: optax>=0.2.6
Requires-Dist: flax>=0.12.1
Provides-Extra: gpu
Requires-Dist: jax[cuda12]>=0.8.1; extra == "gpu"
Provides-Extra: doc
Requires-Dist: jupyterlab; extra == "doc"
Requires-Dist: matplotlib; extra == "doc"
Requires-Dist: scikit-learn; extra == "doc"
Requires-Dist: pytest; extra == "doc"
Requires-Dist: sphinx; extra == "doc"
Requires-Dist: sphinx-rtd-theme; extra == "doc"
Requires-Dist: sphinx-autobuild; extra == "doc"
Requires-Dist: myst-parser; extra == "doc"
Requires-Dist: sphinx_design; extra == "doc"
Requires-Dist: sphinx-autodoc-typehints; extra == "doc"
Requires-Dist: nbsphinx; extra == "doc"
Requires-Dist: nbsphinx-link; extra == "doc"
Requires-Dist: pandoc; extra == "doc"
Dynamic: license-file
